pulpcore/__init__.py
pulpcore/client/__init__.py
pulpcore/client/pulp_cookbook/__init__.py
pulpcore/client/pulp_cookbook/api_client.py
pulpcore/client/pulp_cookbook/configuration.py
pulpcore/client/pulp_cookbook/exceptions.py
pulpcore/client/pulp_cookbook/rest.py
pulpcore/client/pulp_cookbook/api/__init__.py
pulpcore/client/pulp_cookbook/api/content_cookbooks_api.py
pulpcore/client/pulp_cookbook/api/distributions_cookbook_api.py
pulpcore/client/pulp_cookbook/api/publications_cookbook_api.py
pulpcore/client/pulp_cookbook/api/remotes_cookbook_api.py
pulpcore/client/pulp_cookbook/api/repositories_cookbook_api.py
pulpcore/client/pulp_cookbook/api/repositories_cookbook_versions_api.py
pulpcore/client/pulp_cookbook/models/__init__.py
pulpcore/client/pulp_cookbook/models/async_operation_response.py
pulpcore/client/pulp_cookbook/models/content_summary_response.py
pulpcore/client/pulp_cookbook/models/cookbook_cookbook_distribution.py
pulpcore/client/pulp_cookbook/models/cookbook_cookbook_distribution_response.py
pulpcore/client/pulp_cookbook/models/cookbook_cookbook_package_content.py
pulpcore/client/pulp_cookbook/models/cookbook_cookbook_package_content_response.py
pulpcore/client/pulp_cookbook/models/cookbook_cookbook_publication.py
pulpcore/client/pulp_cookbook/models/cookbook_cookbook_publication_response.py
pulpcore/client/pulp_cookbook/models/cookbook_cookbook_remote.py
pulpcore/client/pulp_cookbook/models/cookbook_cookbook_remote_response.py
pulpcore/client/pulp_cookbook/models/cookbook_cookbook_repository.py
pulpcore/client/pulp_cookbook/models/cookbook_cookbook_repository_response.py
pulpcore/client/pulp_cookbook/models/paginated_repository_version_response_list.py
pulpcore/client/pulp_cookbook/models/paginatedcookbook_cookbook_distribution_response_list.py
pulpcore/client/pulp_cookbook/models/paginatedcookbook_cookbook_package_content_response_list.py
pulpcore/client/pulp_cookbook/models/paginatedcookbook_cookbook_publication_response_list.py
pulp_cookbook_client-0.1.0b10.dev1658548279.dist-info/METADATA
pulp_cookbook_client-0.1.0b10.dev1658548279.dist-info/WHEEL
pulp_cookbook_client-0.1.0b10.dev1658548279.dist-info/top_level.txt
pulp_cookbook_client-0.1.0b10.dev1658548279.dist-info/RECORD
