Metadata-Version: 2.1
Name: pulp-cookbook-client
Version: 0.1.0b10.dev1658548279
Summary: Pulp 3 API
Home-page: UNKNOWN
Author: Pulp Team
Author-email: pulp-list@redhat.com
License: GPLv2+
Keywords: pulp,pulpcore,client,Pulp 3 API
Platform: UNKNOWN
Requires-Python: >=3.4
Requires-Dist: urllib3 (>=1.15)
Requires-Dist: six (>=1.10)
Requires-Dist: certifi
Requires-Dist: python-dateutil
